digitalhub_runtime_mlrun/__init__.py
digitalhub_runtime_mlrun/entities/__init__.py
digitalhub_runtime_mlrun/entities/functions/__init__.py
digitalhub_runtime_mlrun/entities/functions/spec.py
digitalhub_runtime_mlrun/entities/functions/status.py
digitalhub_runtime_mlrun/entities/runs/__init__.py
digitalhub_runtime_mlrun/entities/runs/spec.py
digitalhub_runtime_mlrun/entities/runs/status.py
digitalhub_runtime_mlrun/entities/tasks/__init__.py
digitalhub_runtime_mlrun/entities/tasks/spec.py
digitalhub_runtime_mlrun/entities/tasks/status.py
digitalhub_runtime_mlrun/runtimes/__init__.py
digitalhub_runtime_mlrun/runtimes/kind_registry.py
digitalhub_runtime_mlrun/runtimes/runtime.py
digitalhub_runtime_mlrun/utils/__init__.py
digitalhub_runtime_mlrun/utils/configurations.py
digitalhub_runtime_mlrun/utils/env.py
digitalhub_runtime_mlrun/utils/functions.py
digitalhub_runtime_mlrun/utils/inputs.py
digitalhub_runtime_mlrun/utils/outputs.py
digitalhub_runtime_mlrun-0.6.0.dist-info/LICENSE.txt
digitalhub_runtime_mlrun-0.6.0.dist-info/METADATA
digitalhub_runtime_mlrun-0.6.0.dist-info/WHEEL
digitalhub_runtime_mlrun-0.6.0.dist-info/top_level.txt
digitalhub_runtime_mlrun-0.6.0.dist-info/RECORD
