Metadata-Version: 2.1
Name: digitalhub-runtime-mlrun
Version: 0.6.0
Summary: Mlrun runtime for DHCore
Author-email: Fondazione Bruno Kessler <dslab@fbk.eu>, Matteo Martini <mmartini@fbk.eu>
License: Apache License
Project-URL: Homepage, https://github.com/scc-digitalhub/digitalhub-sdk
Keywords: data,dataops,kubernetes
Classifier: License :: OSI Approved :: Apache Software License
Classifier: Programming Language :: Python :: 3.9
Requires-Python: >=3.9
License-File: LICENSE.txt
Requires-Dist: digitalhub[ml] >=0.6.0b
Requires-Dist: digitalhub-core[full] >=0.6.0b
Provides-Extra: local
Requires-Dist: mlrun ==1.6.2rc1 ; extra == 'local'
Requires-Dist: s3fs ; extra == 'local'
